{
  "bad": [],
  "errs": [],
  "data": {
    "dock": {
      "x": 22,
      "y": 760,
      "width": 346,
      "height": 68,
      "display": "grid",
      "radius": "18px",
      "opacity": "1"
    },
    "dockLinks": [
      {
        "text": "Home",
        "active": false,
        "rect": {
          "x": 31,
          "y": 769,
          "width": 62,
          "height": 50
        },
        "radius": "12px",
        "color": "rgb(182, 178, 170)",
        "bg": "rgba(0, 0, 0, 0)"
      },
      {
        "text": "Races",
        "active": false,
        "rect": {
          "x": 97,
          "y": 769,
          "width": 62,
          "height": 50
        },
        "radius": "12px",
        "color": "rgb(182, 178, 170)",
        "bg": "rgba(0, 0, 0, 0)"
      },
      {
        "text": "Results",
        "active": false,
        "rect": {
          "x": 164,
          "y": 769,
          "width": 62,
          "height": 50
        },
        "radius": "12px",
        "color": "rgb(182, 178, 170)",
        "bg": "rgba(0, 0, 0, 0)"
      },
      {
        "text": "Dogs",
        "active": false,
        "rect": {
          "x": 230,
          "y": 769,
          "width": 62,
          "height": 50
        },
        "radius": "12px",
        "color": "rgb(182, 178, 170)",
        "bg": "rgba(0, 0, 0, 0)"
      },
      {
        "text": "Pro",
        "active": true,
        "rect": {
          "x": 297,
          "y": 769,
          "width": 62,
          "height": 50
        },
        "radius": "12px",
        "color": "rgb(247, 246, 243)",
        "bg": "rgb(112, 29, 150)"
      }
    ],
    "cards": [
      {
        "x": 24,
        "y": 257,
        "width": 342,
        "height": 460
      },
      {
        "x": 24,
        "y": 733,
        "width": 342,
        "height": 531
      },
      {
        "x": 24,
        "y": 1280,
        "width": 342,
        "height": 475
      }
    ],
    "rows": 3,
    "colsFirstRow": 1,
    "minControlHeight": 44,
    "controlsBelow44": []
  }
}