[
  {
    "label": "Home",
    "file": "E:\\greyhoundiq\\output\\design-system-full-audit\\http-html-screenshots\\ui-kit-screen-home.png"
  },
  {
    "label": "Races",
    "file": "E:\\greyhoundiq\\output\\design-system-full-audit\\http-html-screenshots\\ui-kit-screen-races.png"
  },
  {
    "label": "Results",
    "file": "E:\\greyhoundiq\\output\\design-system-full-audit\\http-html-screenshots\\ui-kit-screen-results.png"
  },
  {
    "label": "Dogs",
    "file": "E:\\greyhoundiq\\output\\design-system-full-audit\\http-html-screenshots\\ui-kit-screen-dogs.png"
  },
  {
    "label": "Tracks",
    "file": "E:\\greyhoundiq\\output\\design-system-full-audit\\http-html-screenshots\\ui-kit-screen-tracks.png"
  },
  {
    "label": "Breeding",
    "file": "E:\\greyhoundiq\\output\\design-system-full-audit\\http-html-screenshots\\ui-kit-screen-breeding.png"
  },
  {
    "label": "Agents",
    "file": "E:\\greyhoundiq\\output\\design-system-full-audit\\http-html-screenshots\\ui-kit-screen-agents.png"
  },
  {
    "label": "Forum",
    "file": "E:\\greyhoundiq\\output\\design-system-full-audit\\http-html-screenshots\\ui-kit-screen-forum.png"
  },
  {
    "label": "Listings",
    "file": "E:\\greyhoundiq\\output\\design-system-full-audit\\http-html-screenshots\\ui-kit-screen-listings.png"
  },
  {
    "label": "Pricing",
    "file": "E:\\greyhoundiq\\output\\design-system-full-audit\\http-html-screenshots\\ui-kit-screen-pricing.png"
  }
]